ocean_runner/__init__.py
ocean_runner/config.py
ocean_runner/runner.py
ocean_runner-0.2.21.dist-info/METADATA
ocean_runner-0.2.21.dist-info/WHEEL
ocean_runner-0.2.21.dist-info/licenses/LICENSE
ocean_runner-0.2.21.dist-info/RECORD
