Metadata-Version: 2.4
Name: ocean-runner
Version: 0.2.21
Summary: A fluent API for OceanProtocol algorithms
Project-URL: Homepage, https://github.com/AgrospAI/ocean-runner
Project-URL: Issues, https://github.com/AgrospAI/ocean-runner/issues
Author-email: AgrospAI <agrospai@udl.cat>, Christian López <christian.lopez@udl.cat>
License: Copyright 2025 spin3l
License-File: LICENSE
Classifier: License :: OSI Approved :: MIT License
Classifier: Operating System :: OS Independent
Classifier: Programming Language :: Python :: 3
Requires-Python: >=3.10
Requires-Dist: aiofiles>=25.1.0
Requires-Dist: oceanprotocol-job-details>=0.2.8
Requires-Dist: pydantic-settings>=2.12.0
Requires-Dist: pydantic>=2.12.5
Requires-Dist: pytest>=8.4.2
Requires-Dist: types-aiofiles>=25.1.0.20251011
